Pyment-0.3.3.dist-info/METADATA
Pyment-0.3.3.dist-info/RECORD
Pyment-0.3.3.dist-info/WHEEL
Pyment-0.3.3.dist-info/entry_points.txt
Pyment-0.3.3.dist-info/top_level.txt
pyment/__init__.py
pyment/docstring.py
pyment/pyment.py
pyment/pymentapp.py
