Metadata-Version: 2.1
Name: Pyment
Version: 0.3.3
Summary: Generate/convert automatically the docstrings from code signature
Home-page: https://github.com/dadadel/pyment
Author: A. Daouzli
Author-email: dadel@hadoly.fr
License: GPLv3
Keywords: pyment docstring numpydoc googledoc restructuredtext epydoc epytext javadoc development generate auto
Platform: any
Classifier: Intended Audience :: Developers
Classifier: Topic :: Documentation
Classifier: License :: OSI Approved :: GNU General Public License v3 (GPLv3)
Classifier: Programming Language :: Python :: 2.7
Classifier: Programming Language :: Python :: 3
Classifier: Programming Language :: Python :: 3.0
Classifier: Programming Language :: Python :: 3.1
Classifier: Programming Language :: Python :: 3.2
Classifier: Programming Language :: Python :: 3.3
Classifier: Programming Language :: Python :: 3.4
Classifier: Programming Language :: Python :: 3.5
Classifier: Programming Language :: Python :: 3.6
